WaterTankMonitoringSystem_pkg/APIWaterTank_3.py
WaterTankMonitoringSystem_pkg/__init__.py
WaterTankMonitoringSystem_pkg_THRMAT007_LKYROS001-0.0.2.dist-info/LICENSE
WaterTankMonitoringSystem_pkg_THRMAT007_LKYROS001-0.0.2.dist-info/METADATA
WaterTankMonitoringSystem_pkg_THRMAT007_LKYROS001-0.0.2.dist-info/WHEEL
WaterTankMonitoringSystem_pkg_THRMAT007_LKYROS001-0.0.2.dist-info/top_level.txt
WaterTankMonitoringSystem_pkg_THRMAT007_LKYROS001-0.0.2.dist-info/RECORD
