Metadata-Version: 2.1
Name: WaterTankMonitoringSystem-pkg-THRMAT007-LKYROS001
Version: 0.0.2
Summary: Design project
Home-page: https://github.com/THRMAT007/EEE3097SProject
Author: THRMAT007
Author-email: THRMAT007&@myuct.ac.za
License: UNKNOWN
Platform: UNKNOWN
Classifier: Programming Language :: Python :: 3
Classifier: License :: OSI Approved :: MIT License
Classifier: Operating System :: OS Independent
Requires-Python: >=3.6
Requires-Dist: VL53L1X
Requires-Dist: adafruit-circuitpython-mcp3xxx
Requires-Dist: board
Requires-Dist: busio
Requires-Dist: datetime
Requires-Dist: digitalio
Requires-Dist: io
Requires-Dist: keyboard
Requires-Dist: os
Requires-Dist: re
Requires-Dist: sqlite3
Requires-Dist: time
